c3s_magic_wps/__init__.py
c3s_magic_wps/__version__.py
c3s_magic_wps/cli.py
c3s_magic_wps/default.cfg
c3s_magic_wps/execute.py
c3s_magic_wps/runner.py
c3s_magic_wps/util.py
c3s_magic_wps/wsgi.py
c3s_magic_wps/processes/__init__.py
c3s_magic_wps/processes/wps_blocking.py
c3s_magic_wps/processes/wps_capacity_factor.py
c3s_magic_wps/processes/wps_combined_indices.py
c3s_magic_wps/processes/wps_consecdrydays.py
c3s_magic_wps/processes/wps_cvdp.py
c3s_magic_wps/processes/wps_diurnal_temperature_index.py
c3s_magic_wps/processes/wps_drought_indicator.py
c3s_magic_wps/processes/wps_ensclus.py
c3s_magic_wps/processes/wps_extreme_events.py
c3s_magic_wps/processes/wps_extreme_index.py
c3s_magic_wps/processes/wps_heatwaves_coldwaves.py
c3s_magic_wps/processes/wps_hyint.py
c3s_magic_wps/processes/wps_meta.py
c3s_magic_wps/processes/wps_modes_variability.py
c3s_magic_wps/processes/wps_multimodel_products.py
c3s_magic_wps/processes/wps_perfmetrics.py
c3s_magic_wps/processes/wps_preproc_example.py
c3s_magic_wps/processes/wps_quantilebias.py
c3s_magic_wps/processes/wps_rainfarm.py
c3s_magic_wps/processes/wps_shapeselect.py
c3s_magic_wps/processes/wps_sleep.py
c3s_magic_wps/processes/wps_smpi.py
c3s_magic_wps/processes/wps_teleconnections.py
c3s_magic_wps/processes/wps_toymodel.py
c3s_magic_wps/processes/wps_weather_regimes.py
c3s_magic_wps/processes/wps_zmnam.py
c3s_magic_wps/processes/utils/__init__.py
c3s_magic_wps/processes/utils/data_finder.py
c3s_magic_wps/processes/utils/esmvaltool_utils.py
c3s_magic_wps/static/available_models.json
c3s_magic_wps/static/diagnosticsdata/index.yml
c3s_magic_wps/static/diagnosticsdata/annularmodes/CMIP5_MPI-ESM-MR_amip_r1i1p1_1979-2008_250hPa_da_pdf.png
c3s_magic_wps/static/diagnosticsdata/annularmodes/CMIP5_MPI-ESM-MR_amip_r1i1p1_1979-2008_250hPa_mo_ts.png
c3s_magic_wps/static/diagnosticsdata/annularmodes/annularmodes.yml
c3s_magic_wps/static/diagnosticsdata/annularmodes/annularmodes_thumbnail.png
c3s_magic_wps-1.0.0rc1.dist-info/LICENSE.txt
c3s_magic_wps-1.0.0rc1.dist-info/METADATA
c3s_magic_wps-1.0.0rc1.dist-info/WHEEL
c3s_magic_wps-1.0.0rc1.dist-info/entry_points.txt
c3s_magic_wps-1.0.0rc1.dist-info/top_level.txt
c3s_magic_wps-1.0.0rc1.dist-info/RECORD
