Metadata-Version: 2.1
Name: c3s-magic-wps
Version: 1.0.0rc1
Summary: The Web Processing Service for Climate Data Analysis in the MAGIC project.
Home-page: https://github.com/c3s-magic/c3s-magic-wps
Author: ('Berend Weel', 'Ronald van Haren', 'Niels Drost', 'Jaro Camphuijsen', 'Bouwe Andela', 'Yifat Dzigan')
Author-email: b.weel@esciencecenter.nl
License: Apache Software License 2.0
Keywords: wps pywps birdhouse c3s_magic_wps
Platform: UNKNOWN
Classifier: Development Status :: 5 - Production/Stable
Classifier: Intended Audience :: Developers
Classifier: Intended Audience :: Science/Research
Classifier: Operating System :: MacOS :: MacOS X
Classifier: Operating System :: POSIX
Classifier: Programming Language :: Python
Classifier: Natural Language :: English
Classifier: Programming Language :: Python :: 3
Classifier: Programming Language :: Python :: 3.6
Classifier: Topic :: Scientific/Engineering :: Atmospheric Science
Classifier: License :: OSI Approved :: Apache Software License
Requires-Dist: pywps (>=4.2.0)
Requires-Dist: jinja2
Requires-Dist: click
Requires-Dist: psutil
